{ "columns":0,
 "grid":
    {
     "height":1,
     "orientation":"orthogonal",
     "width":1
    },
 "margin":0,
 "name":"main",
 "spacing":0,
 "tilecount":12,
 "tiledversion":"1.9.2",
 "tileheight":32,
 "tilerendersize":"grid",
 "tiles":[
        {
         "id":15,
         "image":"..\/tileset_gfx\/wall_pillar_1.png",
         "imageheight":32,
         "imagewidth":32,
         "properties":[
                {
                 "name":"activators",
                 "type":"string",
                 "value":"[{\"height\":30}]"
                }]
        }, 
        {
         "id":22,
         "image":"..\/tileset_gfx\/wall_tl_end.png",
         "imageheight":32,
         "imagewidth":32,
         "properties":[
                {
                 "name":"activators",
                 "type":"string",
                 "value":"[{\"height\":30}]"
                }]
        }, 
        {
         "id":26,
         "image":"..\/tileset_gfx\/wall_window_barred_2.png",
         "imageheight":32,
         "imagewidth":32,
         "properties":[
                {
                 "name":"activators",
                 "type":"string",
                 "value":"[{\"height\":30}]"
                }]
        }, 
        {
         "id":24,
         "image":"..\/tileset_gfx\/wall_window_2.png",
         "imageheight":32,
         "imagewidth":32,
         "properties":[
                {
                 "name":"activators",
                 "type":"string",
                 "value":"[{\"height\":30}]"
                }]
        }, 
        {
         "id":13,
         "image":"..\/tileset_gfx\/wall_2.png",
         "imageheight":32,
         "imagewidth":32,
         "properties":[
                {
                 "name":"activators",
                 "type":"string",
                 "value":"[{\"height\":30}]"
                }]
        }, 
        {
         "id":16,
         "image":"..\/tileset_gfx\/wall_pillar_2.png",
         "imageheight":32,
         "imagewidth":32,
         "properties":[
                {
                 "name":"activators",
                 "type":"string",
                 "value":"[{\"height\":30}]"
                }]
        }, 
        {
         "id":20,
         "image":"..\/tileset_gfx\/wall_bl_end.png",
         "imageheight":32,
         "imagewidth":32,
         "properties":[
                {
                 "name":"activators",
                 "type":"string",
                 "value":"[{\"height\":30}]"
                }]
        }, 
        {
         "id":25,
         "image":"..\/tileset_gfx\/wall_window_barred_1.png",
         "imageheight":32,
         "imagewidth":32,
         "properties":[
                {
                 "name":"activators",
                 "type":"string",
                 "value":"[{\"height\":30}]"
                }]
        }, 
        {
         "id":23,
         "image":"..\/tileset_gfx\/wall_window_1.png",
         "imageheight":32,
         "imagewidth":32,
         "properties":[
                {
                 "name":"activators",
                 "type":"string",
                 "value":"[{\"height\":30}]"
                }]
        }, 
        {
         "id":12,
         "image":"..\/tileset_gfx\/wall_1.png",
         "imageheight":32,
         "imagewidth":32,
         "properties":[
                {
                 "name":"activators",
                 "type":"string",
                 "value":"[{\"height\":30}]"
                }]
        }, 
        {
         "id":11,
         "image":"..\/tileset_gfx\/floor_stone.png",
         "imageheight":32,
         "imagewidth":32
        }, 
        {
         "id":17,
         "image":"..\/tileset_gfx\/wall_cap.png",
         "imageheight":32,
         "imagewidth":32,
         "properties":[
                {
                 "name":"activators",
                 "type":"string",
                 "value":"[{\"start_y\":24,\"height\":8}]"
                }]
        }],
 "tilewidth":32,
 "type":"tileset",
 "version":"1.9"
}